LICENSE
MANIFEST.in
README.md
pyproject.toml
batogram/__init__.py
batogram/__main__.py
batogram/about.py
batogram/amplitudegraphframe.py
batogram/appsettings.py
batogram/appsettingsmodal.py
batogram/audiofileservice.py
batogram/breadcrumbservice.py
batogram/browseractionsmodal.py
batogram/browserframe.py
batogram/buttonframe.py
batogram/chunky_spectrogram.py
batogram/colourmap.py
batogram/common.py
batogram/constants.py
batogram/fileinfoframe.py
batogram/frames.py
batogram/graphsettings.py
batogram/historianservice.py
batogram/imagebutton.py
batogram/layouts.py
batogram/markers.py
batogram/modalwindow.py
batogram/morebncframe.py
batogram/moreframe.py
batogram/moreotherframe.py
batogram/morerenderingframe.py
batogram/morescaleframe.py
batogram/playbackmodal.py
batogram/playbackservice.py
batogram/profilegraphframe.py
batogram/readoutframe.py
batogram/renderingservice.py
batogram/rootwindow.py
batogram/runner.py
batogram/spectrogramgraphframe.py
batogram/spectrogrammouseservice.py
batogram/stegangraphy.py
batogram/validatingwidgets.py
batogram/wavfileparser.py
batogram.egg-info/PKG-INFO
batogram.egg-info/SOURCES.txt
batogram.egg-info/dependency_links.txt
batogram.egg-info/entry_points.txt
batogram.egg-info/requires.txt
batogram.egg-info/top_level.txt
batogram/assets/3669170_home_ic_icon.png
batogram/assets/arrow-left-circle-line.png
batogram/assets/arrow-left-line.png
batogram/assets/arrow-right-circle-line.png
batogram/assets/arrow-right-line.png
batogram/assets/batogram.png
batogram/assets/download-line.png
batogram/assets/drag-move-2-line.png
batogram/assets/expand-left-right-fill.png
batogram/assets/expand-up-down-fill.png
batogram/assets/flag-fill.png
batogram/assets/fullscreen-line.png
batogram/assets/home-4-line.png
batogram/assets/pause-fill.png
batogram/assets/pause-line.png
batogram/assets/play-fill.png
batogram/assets/play-line.png
batogram/assets/refresh-line.png
batogram/assets/settings-5-line.png
batogram/assets/stop-fill.png
batogram/assets/stop-line.png
batogram/assets/transparent.png
batogram/assets/zoom-in-line.png
batogram/colour_maps/CET-L01.csv
batogram/colour_maps/CET-L03.csv
batogram/colour_maps/CET-L05.csv
