Metadata-Version: 2.1
Name: batogram
Version: 1.5.0
Summary: Batogram is a GUI program for rendering spectrograms from full spectrum recordings of bat calls.
Author-email: John Mears <john+batogram@themears.co.uk>
License: Copyright (c) 2023 John Mears
Project-URL: Homepage, https://github.com/jmears63/batogram
Keywords: bat,spectrogram,chiropterology,fourier,ultrasonic,ultrasound,echo,GUANO
Classifier: Development Status :: 5 - Production/Stable
Classifier: Intended Audience :: Science/Research
Classifier: Programming Language :: Python :: 3
Classifier: License :: OSI Approved :: MIT License
Classifier: Operating System :: OS Independent
Classifier: Topic :: Multimedia :: Sound/Audio :: Analysis
Requires-Python: >=3.9
License-File: LICENSE
Requires-Dist: numpy
Requires-Dist: scipy
Requires-Dist: Pillow
Requires-Dist: argparse
Requires-Dist: dataclasses-json
Requires-Dist: platformdirs
Requires-Dist: PyAudio
Requires-Dist: hsluv
Requires-Dist: Send2Trash
